{
  "handle": "timeoutbangkok",
  "category": "市集",
  "shortCode": "DZ__z44m5MY",
  "postUrl": "https://www.instagram.com/p/DZ__z44m5MY/",
  "timestamp": "2026-06-25T07:09:18.000Z",
  "type": "Image",
  "images": [
    "data/timeoutbangkok/DZ__z44m5MY/image_1.jpg"
  ],
  "place": "House Samyan",
  "vibe_tags": [
    "文青",
    "熱鬧",
    "浪漫"
  ],
  "date_score": 8,
  "summary": "House Samyan 影城慶祝 22 週年，整個 7 月都有特別活動和電影放映，包含韋斯·安德森的經典電影《皇家特能班》。這是一個適合電影愛好者的好去處，享受電影的同時也能感受到浪漫的氛圍。",
  "end_date": "2023-07-31"
}